README.txt
ecco_dde.py
setup.cfg
setup.py
wikiup.cfg
EccoDDE.egg-info/PKG-INFO
EccoDDE.egg-info/SOURCES.txt
EccoDDE.egg-info/dependency_links.txt
EccoDDE.egg-info/top_level.txt