Metadata-Version: 1.0
Name: EccoDDE
Version: 0.9.1
Summary: Thin wrapper over the Ecco Personal Information Manager's DDE API
Home-page: http://pypi.python.org/pypi/EccoDDE
Author: Phillip J. Eby
Author-email: peak@eby-sarna.com
License: PSF or ZPL
Download-URL: http://peak.telecommunity.com/snapshots/
Platform: UNKNOWN
